alohapy/__init__.py
alohapy/main.py
alohapy-0.2.2.dist-info/METADATA
alohapy-0.2.2.dist-info/WHEEL
alohapy-0.2.2.dist-info/entry_points.txt
alohapy-0.2.2.dist-info/top_level.txt
alohapy-0.2.2.dist-info/RECORD
