Metadata-Version: 2.1
Name: alohapy
Version: 0.2.2
